pretix_closer2event/__init__.py
pretix_closer2event/apps.py
pretix_closer2event/signals.py
pretix_closer2event/urls.py
pretix_closer2event/views.py
pretix_closer2event/locale/django.pot
pretix_closer2event/locale/de/LC_MESSAGES/django.mo
pretix_closer2event/locale/de/LC_MESSAGES/django.po
pretix_closer2event/locale/de_Informal/.gitkeep
pretix_closer2event/locale/de_Informal/LC_MESSAGES/django.mo
pretix_closer2event/locale/de_Informal/LC_MESSAGES/django.po
pretix_closer2event/static/pretix_closer2event/.gitkeep
pretix_closer2event/static/pretix_closer2event/postamble.scss
pretix_closer2event/templates/pretix_closer2event/.gitkeep
pretix_closer2event/templates/pretix_closer2event/order_info.html
pretix_closer2event/templates/pretix_closer2event/presale_css.html
pretix_closer2event/templates/pretix_closer2event/settings.html
pretix_closer2event-1.3.0.dist-info/LICENSE
pretix_closer2event-1.3.0.dist-info/METADATA
pretix_closer2event-1.3.0.dist-info/WHEEL
pretix_closer2event-1.3.0.dist-info/entry_points.txt
pretix_closer2event-1.3.0.dist-info/top_level.txt
pretix_closer2event-1.3.0.dist-info/RECORD
