Metadata-Version: 2.1
Name: pretix-closer2event
Version: 1.3.0
Summary: This plugin allows to integrate the closer2event hotel map into your pretix shop
Author-email: pretix team <support@pretix.eu>
Maintainer-email: pretix team <support@pretix.eu>
License: 
Project-URL: homepage, https://github.com/pretix/pretix-closer2event
Keywords: pretix
Requires-Python: >=3.9
License-File: LICENSE
